fluent_validation/AsyncValidatorInvokedSynchronouslyException.py
fluent_validation/DefaultValidatorExtensions.py
fluent_validation/DefaultValidatorExtensions_Validate.py
fluent_validation/DefaultValidatorOptions.py
fluent_validation/ICollectionRule.py
fluent_validation/IValidationContext.py
fluent_validation/IValidationRule.py
fluent_validation/IValidationRuleInternal.py
fluent_validation/IValidator.py
fluent_validation/InlineValidator.py
fluent_validation/LambdaExpression.py
fluent_validation/MemberInfo.py
fluent_validation/ValidationException.py
fluent_validation/ValidatorOptions.py
fluent_validation/__init__.py
fluent_validation/abstract_validator.py
fluent_validation/enums.py
fluent_validation/internal/AccessorCache.py
fluent_validation/internal/ChildRulesContainer.py
fluent_validation/internal/CollectionPropertyRule.py
fluent_validation/internal/CompositeValidatorSelector.py
fluent_validation/internal/ConditionBuilder.py
fluent_validation/internal/DefaultValidatorSelector.py
fluent_validation/internal/ExtensionInternal.py
fluent_validation/internal/IRuleComponent.py
fluent_validation/internal/IValidatorSelector.py
fluent_validation/internal/IncludeRule.py
fluent_validation/internal/MemberNameValidatorSelector.py
fluent_validation/internal/MessageBuilderContext.py
fluent_validation/internal/MessageFormatter.py
fluent_validation/internal/PropertyChain.py
fluent_validation/internal/PropertyRule.py
fluent_validation/internal/Resources/ILanguageManager.py
fluent_validation/internal/Resources/LanguageManager.py
fluent_validation/internal/Resources/Lenguages/AlbanianLanguage.py
fluent_validation/internal/Resources/Lenguages/ArabicLanguage.py
fluent_validation/internal/Resources/Lenguages/AzerbaijaneseLanguage.py
fluent_validation/internal/Resources/Lenguages/BengaliLanguage.py
fluent_validation/internal/Resources/Lenguages/BosnianLanguage.py
fluent_validation/internal/Resources/Lenguages/BulgarianLanguage.py
fluent_validation-4.3.31.dist-info/AUTHORS
fluent_validation-4.3.31.dist-info/LICENSE
fluent_validation-4.3.31.dist-info/METADATA
fluent_validation-4.3.31.dist-info/WHEEL
fluent_validation-4.3.31.dist-info/RECORD
