Metadata-Version: 2.1
Name: fluent_validation
Version: 4.3.31
Summary: A popular .NET validation library developed by 'Jeremy Skinner' for building strongly-typed validation rules, rewritten in python by 'Pablo Hernández'
License: Apache
Author: p-hzamora
Author-email: p.hzamora@icloud.com
Requires-Python: >=3.12,<4.0
Classifier: License :: Other/Proprietary License
Classifier: Programming Language :: Python :: 3
Classifier: Programming Language :: Python :: 3.12
